{
  "properties": [
    {
      "name": "game.secondsBeforeStart",
      "type": "java.lang.String",
      "description": "Description for game.secondsBeforeStart."
    },
    {
      "name": "game.secondsBeforeStep",
      "type": "java.lang.String",
      "description": "Description for game.secondsBeforeStep."
    },
    {
      "name": "game.maxAttemptsForStep",
      "type": "java.lang.String",
      "description": "Description for game.maxAttemptsForStep."
    },
    {
      "name": "game.maxAttemptsForStart",
      "type": "java.lang.String",
      "description": "Description for game.maxAttemptsForStart."
    },
    {
      "name": "game.maxGames",
      "type": "java.lang.String",
      "description": "Description for game.maxGames."
    },
    {
      "name": "telegram.token",
      "type": "java.lang.String",
      "description": "Description for telegram.token."
    },
    {
      "name": "telegram.chat",
      "type": "java.lang.String",
      "description": "Description for telegram.chat."
    },
    {
      "name": "game.secretKey",
      "type": "java.lang.String",
      "description": "Description for game.secretKey."
    }
  ]
}
